{
    "description": "",
    "tags": [
        {
            "id": 4069151,
            "tagId": 17055,
            "name": "scene",
            "value": "outdoor, urban, street",
            "labelerLogin": "cx@datasetninja.com",
            "createdAt": "2023-09-15T14:11:04.823Z",
            "updatedAt": "2023-09-15T14:11:04.823Z"
        }
    ],
    "size": {
        "height": 256,
        "width": 256
    },
    "objects": [
        {
            "id": 44659896,
            "classId": 55703,
            "description": "",
            "geometryType": "polygon",
            "labelerLogin": "cx@datasetninja.com",
            "createdAt": "2023-09-15T14:11:04.833Z",
            "updatedAt": "2023-09-15T14:11:04.833Z",
            "tags": [],
            "classTitle": "sky",
            "points": {
                "exterior": [
                    [
                        147,
                        38
                    ],
                    [
                        159,
                        36
                    ],
                    [
                        186,
                        24
                    ],
                    [
                        198,
                        25
                    ],
                    [
                        211,
                        22
                    ],
                    [
                        247,
                        1
                    ],
                    [
                        2,
                        1
                    ],
                    [
                        2,
                        9
                    ],
                    [
                        20,
                        11
                    ],
                    [
                        29,
                        0
                    ],
                    [
                        96,
                        0
                    ],
                    [
                        105,
                        10
                    ],
                    [
                        137,
                        7
                    ],
                    [
                        146,
                        31
                    ]
                ],
                "interior": []
            }
        },
        {
            "id": 44659895,
            "classId": 91468,
            "description": "",
            "geometryType": "polygon",
            "labelerLogin": "cx@datasetninja.com",
            "createdAt": "2023-09-15T14:11:04.832Z",
            "updatedAt": "2023-09-15T14:11:04.832Z",
            "tags": [],
            "classTitle": "hill",
            "points": {
                "exterior": [
                    [
                        245,
                        119
                    ],
                    [
                        244,
                        122
                    ],
                    [
                        238,
                        125
                    ],
                    [
                        233,
                        123
                    ],
                    [
                        225,
                        118
                    ],
                    [
                        224,
                        100
                    ],
                    [
                        212,
                        94
                    ],
                    [
                        200,
                        95
                    ],
                    [
                        199,
                        98
                    ],
                    [
                        141,
                        70
                    ],
                    [
                        141,
                        57
                    ],
                    [
                        159,
                        53
                    ],
                    [
                        147,
                        38
                    ],
                    [
                        167,
                        33
                    ],
                    [
                        186,
                        23
                    ],
                    [
                        194,
                        25
                    ],
                    [
                        209,
                        23
                    ],
                    [
                        249,
                        1
                    ],
                    [
                        255,
                        1
                    ],
                    [
                        255,
                        117
                    ]
                ],
                "interior": []
            }
        },
        {
            "id": 44659894,
            "classId": 56368,
            "description": "",
            "geometryType": "polygon",
            "labelerLogin": "cx@datasetninja.com",
            "createdAt": "2023-09-15T14:11:04.830Z",
            "updatedAt": "2023-09-15T14:11:04.830Z",
            "tags": [],
            "classTitle": "buildings",
            "points": {
                "exterior": [
                    [
                        245,
                        205
                    ],
                    [
                        242,
                        154
                    ],
                    [
                        233,
                        151
                    ],
                    [
                        231,
                        127
                    ],
                    [
                        233,
                        125
                    ],
                    [
                        238,
                        126
                    ],
                    [
                        245,
                        123
                    ],
                    [
                        246,
                        120
                    ],
                    [
                        255,
                        118
                    ],
                    [
                        255,
                        200
                    ]
                ],
                "interior": []
            }
        },
        {
            "id": 44659893,
            "classId": 56158,
            "description": "",
            "geometryType": "polygon",
            "labelerLogin": "cx@datasetninja.com",
            "createdAt": "2023-09-15T14:11:04.830Z",
            "updatedAt": "2023-09-15T14:11:04.830Z",
            "tags": [],
            "classTitle": "building",
            "points": {
                "exterior": [
                    [
                        0,
                        243
                    ],
                    [
                        0,
                        9
                    ],
                    [
                        18,
                        11
                    ],
                    [
                        27,
                        1
                    ],
                    [
                        98,
                        1
                    ],
                    [
                        104,
                        9
                    ],
                    [
                        137,
                        7
                    ],
                    [
                        147,
                        37
                    ],
                    [
                        158,
                        52
                    ],
                    [
                        141,
                        57
                    ],
                    [
                        141,
                        70
                    ],
                    [
                        199,
                        99
                    ],
                    [
                        201,
                        95
                    ],
                    [
                        210,
                        94
                    ],
                    [
                        223,
                        100
                    ],
                    [
                        225,
                        118
                    ],
                    [
                        234,
                        123
                    ],
                    [
                        230,
                        128
                    ],
                    [
                        233,
                        151
                    ],
                    [
                        242,
                        153
                    ],
                    [
                        245,
                        212
                    ],
                    [
                        240,
                        213
                    ],
                    [
                        218,
                        213
                    ],
                    [
                        213,
                        216
                    ],
                    [
                        210,
                        223
                    ],
                    [
                        202,
                        225
                    ],
                    [
                        199,
                        229
                    ],
                    [
                        162,
                        232
                    ],
                    [
                        145,
                        235
                    ],
                    [
                        136,
                        239
                    ],
                    [
                        107,
                        242
                    ],
                    [
                        89,
                        246
                    ],
                    [
                        56,
                        245
                    ],
                    [
                        36,
                        245
                    ]
                ],
                "interior": []
            }
        },
        {
            "id": 44659892,
            "classId": 65179,
            "description": "",
            "geometryType": "polygon",
            "labelerLogin": "cx@datasetninja.com",
            "createdAt": "2023-09-15T14:11:04.830Z",
            "updatedAt": "2023-09-15T14:11:04.830Z",
            "tags": [],
            "classTitle": "fire hydrant",
            "points": {
                "exterior": [
                    [
                        73,
                        253
                    ],
                    [
                        73,
                        248
                    ],
                    [
                        71,
                        247
                    ],
                    [
                        71,
                        244
                    ],
                    [
                        73,
                        243
                    ],
                    [
                        74,
                        238
                    ],
                    [
                        77,
                        237
                    ],
                    [
                        79,
                        239
                    ],
                    [
                        78,
                        242
                    ],
                    [
                        81,
                        244
                    ],
                    [
                        78,
                        246
                    ],
                    [
                        78,
                        252
                    ],
                    [
                        79,
                        255
                    ],
                    [
                        72,
                        255
                    ]
                ],
                "interior": []
            }
        },
        {
            "id": 44659891,
            "classId": 122044,
            "description": "",
            "geometryType": "polygon",
            "labelerLogin": "cx@datasetninja.com",
            "createdAt": "2023-09-15T14:11:04.830Z",
            "updatedAt": "2023-09-15T14:11:04.830Z",
            "tags": [],
            "classTitle": "balcony",
            "points": {
                "exterior": [
                    [
                        67,
                        91
                    ],
                    [
                        76,
                        100
                    ],
                    [
                        93,
                        101
                    ],
                    [
                        106,
                        98
                    ],
                    [
                        106,
                        74
                    ],
                    [
                        106,
                        66
                    ],
                    [
                        98,
                        63
                    ],
                    [
                        97,
                        38
                    ],
                    [
                        75,
                        35
                    ],
                    [
                        75,
                        62
                    ],
                    [
                        68,
                        63
                    ]
                ],
                "interior": []
            }
        },
        {
            "id": 44659890,
            "classId": 122044,
            "description": "",
            "geometryType": "polygon",
            "labelerLogin": "cx@datasetninja.com",
            "createdAt": "2023-09-15T14:11:04.830Z",
            "updatedAt": "2023-09-15T14:11:04.830Z",
            "tags": [],
            "classTitle": "balcony",
            "points": {
                "exterior": [
                    [
                        159,
                        145
                    ],
                    [
                        160,
                        170
                    ],
                    [
                        171,
                        171
                    ],
                    [
                        192,
                        171
                    ],
                    [
                        191,
                        150
                    ],
                    [
                        177,
                        146
                    ],
                    [
                        176,
                        141
                    ],
                    [
                        174,
                        133
                    ],
                    [
                        173,
                        128
                    ],
                    [
                        169,
                        126
                    ],
                    [
                        166,
                        129
                    ],
                    [
                        165,
                        133
                    ],
                    [
                        164,
                        137
                    ],
                    [
                        164,
                        144
                    ]
                ],
                "interior": []
            }
        },
        {
            "id": 44659889,
            "classId": 55829,
            "description": "",
            "geometryType": "polygon",
            "labelerLogin": "cx@datasetninja.com",
            "createdAt": "2023-09-15T14:11:04.830Z",
            "updatedAt": "2023-09-15T14:11:04.830Z",
            "tags": [],
            "classTitle": "door",
            "points": {
                "exterior": [
                    [
                        164,
                        160
                    ],
                    [
                        165,
                        137
                    ],
                    [
                        165,
                        132
                    ],
                    [
                        167,
                        132
                    ],
                    [
                        168,
                        138
                    ],
                    [
                        168,
                        150
                    ],
                    [
                        168,
                        161
                    ]
                ],
                "interior": []
            }
        },
        {
            "id": 44659888,
            "classId": 55136,
            "description": "",
            "geometryType": "polygon",
            "labelerLogin": "cx@datasetninja.com",
            "createdAt": "2023-09-15T14:11:04.829Z",
            "updatedAt": "2023-09-15T14:11:04.829Z",
            "tags": [],
            "classTitle": "window",
            "points": {
                "exterior": [
                    [
                        44,
                        139
                    ],
                    [
                        44,
                        104
                    ],
                    [
                        56,
                        103
                    ],
                    [
                        56,
                        139
                    ]
                ],
                "interior": []
            }
        },
        {
            "id": 44659887,
            "classId": 68911,
            "description": "",
            "geometryType": "polygon",
            "labelerLogin": "cx@datasetninja.com",
            "createdAt": "2023-09-15T14:11:04.829Z",
            "updatedAt": "2023-09-15T14:11:04.829Z",
            "tags": [],
            "classTitle": "pole",
            "points": {
                "exterior": [
                    [
                        159,
                        246
                    ],
                    [
                        159,
                        171
                    ],
                    [
                        161,
                        171
                    ]
                ],
                "interior": []
            }
        },
        {
            "id": 44659886,
            "classId": 59348,
            "description": "",
            "geometryType": "polygon",
            "labelerLogin": "cx@datasetninja.com",
            "createdAt": "2023-09-15T14:11:04.828Z",
            "updatedAt": "2023-09-15T14:11:04.828Z",
            "tags": [],
            "classTitle": "flowerpot",
            "points": {
                "exterior": [
                    [
                        31,
                        253
                    ],
                    [
                        17,
                        253
                    ],
                    [
                        13,
                        251
                    ],
                    [
                        14,
                        237
                    ],
                    [
                        20,
                        237
                    ],
                    [
                        22,
                        234
                    ],
                    [
                        22,
                        229
                    ],
                    [
                        22,
                        200
                    ],
                    [
                        21,
                        199
                    ],
                    [
                        11,
                        198
                    ],
                    [
                        9,
                        194
                    ],
                    [
                        13,
                        189
                    ],
                    [
                        17,
                        188
                    ],
                    [
                        21,
                        189
                    ],
                    [
                        29,
                        189
                    ],
                    [
                        33,
                        190
                    ],
                    [
                        36,
                        192
                    ],
                    [
                        37,
                        194
                    ],
                    [
                        39,
                        198
                    ],
                    [
                        28,
                        200
                    ],
                    [
                        27,
                        199
                    ],
                    [
                        25,
                        200
                    ],
                    [
                        24,
                        236
                    ],
                    [
                        31,
                        237
                    ]
                ],
                "interior": []
            }
        },
        {
            "id": 44659885,
            "classId": 65323,
            "description": "",
            "geometryType": "polygon",
            "labelerLogin": "cx@datasetninja.com",
            "createdAt": "2023-09-15T14:11:04.828Z",
            "updatedAt": "2023-09-15T14:11:04.828Z",
            "tags": [],
            "classTitle": "street light",
            "points": {
                "exterior": [
                    [
                        33,
                        167
                    ],
                    [
                        30,
                        168
                    ],
                    [
                        25,
                        166
                    ],
                    [
                        25,
                        162
                    ],
                    [
                        28,
                        162
                    ],
                    [
                        31,
                        158
                    ],
                    [
                        32,
                        152
                    ],
                    [
                        30,
                        150
                    ],
                    [
                        29,
                        148
                    ],
                    [
                        27,
                        146
                    ],
                    [
                        25,
                        145
                    ],
                    [
                        24,
                        149
                    ],
                    [
                        23,
                        150
                    ],
                    [
                        21,
                        151
                    ],
                    [
                        21,
                        157
                    ],
                    [
                        21,
                        160
                    ],
                    [
                        23,
                        162
                    ],
                    [
                        25,
                        163
                    ],
                    [
                        27,
                        166
                    ]
                ],
                "interior": []
            }
        },
        {
            "id": 44659884,
            "classId": 55829,
            "description": "",
            "geometryType": "polygon",
            "labelerLogin": "cx@datasetninja.com",
            "createdAt": "2023-09-15T14:11:04.828Z",
            "updatedAt": "2023-09-15T14:11:04.828Z",
            "tags": [],
            "classTitle": "door",
            "points": {
                "exterior": [
                    [
                        72,
                        186
                    ],
                    [
                        81,
                        186
                    ],
                    [
                        80,
                        241
                    ],
                    [
                        78,
                        237
                    ],
                    [
                        75,
                        238
                    ],
                    [
                        74,
                        240
                    ],
                    [
                        71,
                        241
                    ],
                    [
                        71,
                        189
                    ]
                ],
                "interior": []
            }
        },
        {
            "id": 44659883,
            "classId": 55136,
            "description": "",
            "geometryType": "polygon",
            "labelerLogin": "cx@datasetninja.com",
            "createdAt": "2023-09-15T14:11:04.828Z",
            "updatedAt": "2023-09-15T14:11:04.828Z",
            "tags": [],
            "classTitle": "window",
            "points": {
                "exterior": [
                    [
                        20,
                        105
                    ],
                    [
                        32,
                        105
                    ],
                    [
                        31,
                        141
                    ],
                    [
                        18,
                        141
                    ]
                ],
                "interior": []
            }
        },
        {
            "id": 44659882,
            "classId": 494336,
            "description": "",
            "geometryType": "polygon",
            "labelerLogin": "cx@datasetninja.com",
            "createdAt": "2023-09-15T14:11:04.828Z",
            "updatedAt": "2023-09-15T14:11:04.828Z",
            "tags": [],
            "classTitle": "shop window",
            "points": {
                "exterior": [
                    [
                        41,
                        225
                    ],
                    [
                        42,
                        187
                    ],
                    [
                        55,
                        187
                    ],
                    [
                        54,
                        224
                    ]
                ],
                "interior": []
            }
        },
        {
            "id": 44659881,
            "classId": 122044,
            "description": "",
            "geometryType": "polygon",
            "labelerLogin": "cx@datasetninja.com",
            "createdAt": "2023-09-15T14:11:04.827Z",
            "updatedAt": "2023-09-15T14:11:04.827Z",
            "tags": [],
            "classTitle": "balcony",
            "points": {
                "exterior": [
                    [
                        66,
                        151
                    ],
                    [
                        82,
                        151
                    ],
                    [
                        92,
                        150
                    ],
                    [
                        97,
                        151
                    ],
                    [
                        98,
                        152
                    ],
                    [
                        106,
                        153
                    ],
                    [
                        107,
                        138
                    ],
                    [
                        105,
                        130
                    ],
                    [
                        97,
                        127
                    ],
                    [
                        94,
                        126
                    ],
                    [
                        94,
                        102
                    ],
                    [
                        71,
                        101
                    ],
                    [
                        72,
                        130
                    ],
                    [
                        65,
                        130
                    ]
                ],
                "interior": []
            }
        },
        {
            "id": 44659880,
            "classId": 55829,
            "description": "",
            "geometryType": "polygon",
            "labelerLogin": "cx@datasetninja.com",
            "createdAt": "2023-09-15T14:11:04.827Z",
            "updatedAt": "2023-09-15T14:11:04.827Z",
            "tags": [],
            "classTitle": "door",
            "points": {
                "exterior": [
                    [
                        76,
                        104
                    ],
                    [
                        90,
                        105
                    ],
                    [
                        89,
                        125
                    ],
                    [
                        82,
                        127
                    ],
                    [
                        81,
                        136
                    ],
                    [
                        75,
                        137
                    ]
                ],
                "interior": []
            }
        },
        {
            "id": 44659879,
            "classId": 55136,
            "description": "",
            "geometryType": "polygon",
            "labelerLogin": "cx@datasetninja.com",
            "createdAt": "2023-09-15T14:11:04.827Z",
            "updatedAt": "2023-09-15T14:11:04.827Z",
            "tags": [],
            "classTitle": "window",
            "points": {
                "exterior": [
                    [
                        150,
                        151
                    ],
                    [
                        151,
                        120
                    ],
                    [
                        145,
                        119
                    ],
                    [
                        144,
                        150
                    ]
                ],
                "interior": []
            }
        },
        {
            "id": 44659878,
            "classId": 122044,
            "description": "",
            "geometryType": "polygon",
            "labelerLogin": "cx@datasetninja.com",
            "createdAt": "2023-09-15T14:11:04.826Z",
            "updatedAt": "2023-09-15T14:11:04.826Z",
            "tags": [],
            "classTitle": "balcony",
            "points": {
                "exterior": [
                    [
                        194,
                        172
                    ],
                    [
                        204,
                        173
                    ],
                    [
                        220,
                        175
                    ],
                    [
                        217,
                        158
                    ],
                    [
                        207,
                        154
                    ],
                    [
                        206,
                        149
                    ],
                    [
                        204,
                        143
                    ],
                    [
                        204,
                        139
                    ],
                    [
                        202,
                        138
                    ],
                    [
                        200,
                        138
                    ],
                    [
                        197,
                        142
                    ],
                    [
                        197,
                        146
                    ],
                    [
                        196,
                        152
                    ],
                    [
                        195,
                        153
                    ]
                ],
                "interior": []
            }
        },
        {
            "id": 44659877,
            "classId": 55829,
            "description": "",
            "geometryType": "polygon",
            "labelerLogin": "cx@datasetninja.com",
            "createdAt": "2023-09-15T14:11:04.826Z",
            "updatedAt": "2023-09-15T14:11:04.826Z",
            "tags": [],
            "classTitle": "door",
            "points": {
                "exterior": [
                    [
                        210,
                        182
                    ],
                    [
                        218,
                        181
                    ],
                    [
                        220,
                        212
                    ],
                    [
                        216,
                        213
                    ],
                    [
                        214,
                        214
                    ],
                    [
                        212,
                        216
                    ],
                    [
                        211,
                        185
                    ]
                ],
                "interior": []
            }
        },
        {
            "id": 44659876,
            "classId": 61099,
            "description": "",
            "geometryType": "polygon",
            "labelerLogin": "cx@datasetninja.com",
            "createdAt": "2023-09-15T14:11:04.826Z",
            "updatedAt": "2023-09-15T14:11:04.826Z",
            "tags": [],
            "classTitle": "car",
            "points": {
                "exterior": [
                    [
                        252,
                        231
                    ],
                    [
                        249,
                        229
                    ],
                    [
                        248,
                        226
                    ],
                    [
                        246,
                        222
                    ],
                    [
                        243,
                        219
                    ],
                    [
                        240,
                        215
                    ],
                    [
                        246,
                        211
                    ],
                    [
                        246,
                        205
                    ],
                    [
                        255,
                        200
                    ],
                    [
                        255,
                        231
                    ]
                ],
                "interior": []
            }
        },
        {
            "id": 44659875,
            "classId": 61099,
            "description": "",
            "geometryType": "polygon",
            "labelerLogin": "cx@datasetninja.com",
            "createdAt": "2023-09-15T14:11:04.826Z",
            "updatedAt": "2023-09-15T14:11:04.826Z",
            "tags": [],
            "classTitle": "car",
            "points": {
                "exterior": [
                    [
                        247,
                        238
                    ],
                    [
                        244,
                        238
                    ],
                    [
                        242,
                        235
                    ],
                    [
                        237,
                        235
                    ],
                    [
                        236,
                        239
                    ],
                    [
                        236,
                        242
                    ],
                    [
                        234,
                        242
                    ],
                    [
                        232,
                        239
                    ],
                    [
                        209,
                        239
                    ],
                    [
                        207,
                        242
                    ],
                    [
                        205,
                        242
                    ],
                    [
                        204,
                        240
                    ],
                    [
                        203,
                        238
                    ],
                    [
                        200,
                        237
                    ],
                    [
                        200,
                        228
                    ],
                    [
                        210,
                        223
                    ],
                    [
                        214,
                        217
                    ],
                    [
                        220,
                        213
                    ],
                    [
                        239,
                        213
                    ],
                    [
                        246,
                        221
                    ],
                    [
                        247,
                        226
                    ],
                    [
                        247,
                        231
                    ],
                    [
                        248,
                        233
                    ],
                    [
                        248,
                        235
                    ]
                ],
                "interior": []
            }
        },
        {
            "id": 44659874,
            "classId": 64199,
            "description": "",
            "geometryType": "polygon",
            "labelerLogin": "cx@datasetninja.com",
            "createdAt": "2023-09-15T14:11:04.825Z",
            "updatedAt": "2023-09-15T14:11:04.825Z",
            "tags": [],
            "classTitle": "sidewalk",
            "points": {
                "exterior": [
                    [
                        2,
                        243
                    ],
                    [
                        88,
                        247
                    ],
                    [
                        107,
                        242
                    ],
                    [
                        134,
                        240
                    ],
                    [
                        143,
                        235
                    ],
                    [
                        198,
                        229
                    ],
                    [
                        199,
                        238
                    ],
                    [
                        202,
                        239
                    ],
                    [
                        204,
                        241
                    ],
                    [
                        186,
                        249
                    ],
                    [
                        161,
                        255
                    ],
                    [
                        0,
                        255
                    ]
                ],
                "interior": []
            }
        },
        {
            "id": 44659873,
            "classId": 56261,
            "description": "",
            "geometryType": "polygon",
            "labelerLogin": "cx@datasetninja.com",
            "createdAt": "2023-09-15T14:11:04.824Z",
            "updatedAt": "2023-09-15T14:11:04.824Z",
            "tags": [],
            "classTitle": "road",
            "points": {
                "exterior": [
                    [
                        203,
                        243
                    ],
                    [
                        255,
                        232
                    ],
                    [
                        255,
                        255
                    ],
                    [
                        163,
                        255
                    ]
                ],
                "interior": []
            }
        },
        {
            "id": 44659872,
            "classId": 55136,
            "description": "",
            "geometryType": "polygon",
            "labelerLogin": "cx@datasetninja.com",
            "createdAt": "2023-09-15T14:11:04.824Z",
            "updatedAt": "2023-09-15T14:11:04.824Z",
            "tags": [],
            "classTitle": "window",
            "points": {
                "exterior": [
                    [
                        21,
                        66
                    ],
                    [
                        22,
                        39
                    ],
                    [
                        30,
                        39
                    ],
                    [
                        28,
                        67
                    ]
                ],
                "interior": []
            }
        },
        {
            "id": 44659871,
            "classId": 55136,
            "description": "",
            "geometryType": "polygon",
            "labelerLogin": "cx@datasetninja.com",
            "createdAt": "2023-09-15T14:11:04.824Z",
            "updatedAt": "2023-09-15T14:11:04.824Z",
            "tags": [],
            "classTitle": "window",
            "points": {
                "exterior": [
                    [
                        47,
                        64
                    ],
                    [
                        48,
                        36
                    ],
                    [
                        55,
                        35
                    ],
                    [
                        55,
                        64
                    ]
                ],
                "interior": []
            }
        },
        {
            "id": 44659870,
            "classId": 494336,
            "description": "",
            "geometryType": "polygon",
            "labelerLogin": "cx@datasetninja.com",
            "createdAt": "2023-09-15T14:11:04.824Z",
            "updatedAt": "2023-09-15T14:11:04.824Z",
            "tags": [],
            "classTitle": "shop window",
            "points": {
                "exterior": [
                    [
                        115,
                        224
                    ],
                    [
                        115,
                        188
                    ],
                    [
                        112,
                        188
                    ],
                    [
                        111,
                        225
                    ]
                ],
                "interior": []
            }
        },
        {
            "id": 44659869,
            "classId": 55829,
            "description": "",
            "geometryType": "polygon",
            "labelerLogin": "cx@datasetninja.com",
            "createdAt": "2023-09-15T14:11:04.823Z",
            "updatedAt": "2023-09-15T14:11:04.823Z",
            "tags": [],
            "classTitle": "door",
            "points": {
                "exterior": [
                    [
                        173,
                        190
                    ],
                    [
                        167,
                        191
                    ],
                    [
                        167,
                        230
                    ],
                    [
                        175,
                        230
                    ]
                ],
                "interior": []
            }
        }
    ]
}