{
    "description": "",
    "tags": [
        {
            "id": 4056892,
            "tagId": 17055,
            "name": "scene",
            "value": "indoor, cultural, art_gallery",
            "labelerLogin": "cx@datasetninja.com",
            "createdAt": "2023-09-15T12:55:04.158Z",
            "updatedAt": "2023-09-15T12:55:04.158Z"
        }
    ],
    "size": {
        "height": 376,
        "width": 500
    },
    "objects": [
        {
            "id": 44251179,
            "classId": 54884,
            "description": "",
            "geometryType": "polygon",
            "labelerLogin": "cx@datasetninja.com",
            "createdAt": "2023-09-15T12:55:04.162Z",
            "updatedAt": "2023-09-15T12:55:04.162Z",
            "tags": [],
            "classTitle": "ceiling",
            "points": {
                "exterior": [
                    [
                        179,
                        84
                    ],
                    [
                        499,
                        23
                    ],
                    [
                        499,
                        0
                    ],
                    [
                        0,
                        0
                    ],
                    [
                        2,
                        66
                    ]
                ],
                "interior": []
            }
        },
        {
            "id": 44251178,
            "classId": 54884,
            "description": "",
            "geometryType": "polygon",
            "labelerLogin": "cx@datasetninja.com",
            "createdAt": "2023-09-15T12:55:04.161Z",
            "updatedAt": "2023-09-15T12:55:04.161Z",
            "tags": [],
            "classTitle": "ceiling",
            "points": {
                "exterior": [
                    [
                        0,
                        116
                    ],
                    [
                        20,
                        119
                    ],
                    [
                        119,
                        96
                    ],
                    [
                        0,
                        84
                    ]
                ],
                "interior": []
            }
        },
        {
            "id": 44251177,
            "classId": 54886,
            "description": "",
            "geometryType": "polygon",
            "labelerLogin": "cx@datasetninja.com",
            "createdAt": "2023-09-15T12:55:04.161Z",
            "updatedAt": "2023-09-15T12:55:04.161Z",
            "tags": [],
            "classTitle": "wall",
            "points": {
                "exterior": [
                    [
                        0,
                        212
                    ],
                    [
                        12,
                        210
                    ],
                    [
                        9,
                        126
                    ],
                    [
                        2,
                        126
                    ]
                ],
                "interior": []
            }
        },
        {
            "id": 44251176,
            "classId": 54886,
            "description": "",
            "geometryType": "polygon",
            "labelerLogin": "cx@datasetninja.com",
            "createdAt": "2023-09-15T12:55:04.161Z",
            "updatedAt": "2023-09-15T12:55:04.161Z",
            "tags": [],
            "classTitle": "wall",
            "points": {
                "exterior": [
                    [
                        22,
                        217
                    ],
                    [
                        19,
                        119
                    ],
                    [
                        0,
                        116
                    ],
                    [
                        2,
                        125
                    ],
                    [
                        10,
                        126
                    ],
                    [
                        11,
                        217
                    ],
                    [
                        15,
                        218
                    ]
                ],
                "interior": []
            }
        },
        {
            "id": 44251175,
            "classId": 54886,
            "description": "",
            "geometryType": "polygon",
            "labelerLogin": "cx@datasetninja.com",
            "createdAt": "2023-09-15T12:55:04.161Z",
            "updatedAt": "2023-09-15T12:55:04.161Z",
            "tags": [],
            "classTitle": "wall",
            "points": {
                "exterior": [
                    [
                        31,
                        217
                    ],
                    [
                        22,
                        217
                    ],
                    [
                        20,
                        119
                    ],
                    [
                        119,
                        96
                    ],
                    [
                        152,
                        96
                    ],
                    [
                        156,
                        252
                    ],
                    [
                        147,
                        252
                    ],
                    [
                        148,
                        242
                    ]
                ],
                "interior": []
            }
        },
        {
            "id": 44251174,
            "classId": 54886,
            "description": "",
            "geometryType": "polygon",
            "labelerLogin": "cx@datasetninja.com",
            "createdAt": "2023-09-15T12:55:04.161Z",
            "updatedAt": "2023-09-15T12:55:04.161Z",
            "tags": [],
            "classTitle": "wall",
            "points": {
                "exterior": [
                    [
                        181,
                        249
                    ],
                    [
                        158,
                        253
                    ],
                    [
                        150,
                        95
                    ],
                    [
                        0,
                        83
                    ],
                    [
                        2,
                        65
                    ],
                    [
                        179,
                        85
                    ]
                ],
                "interior": []
            }
        },
        {
            "id": 44251173,
            "classId": 54886,
            "description": "",
            "geometryType": "polygon",
            "labelerLogin": "cx@datasetninja.com",
            "createdAt": "2023-09-15T12:55:04.161Z",
            "updatedAt": "2023-09-15T12:55:04.161Z",
            "tags": [],
            "classTitle": "wall",
            "points": {
                "exterior": [
                    [
                        499,
                        312
                    ],
                    [
                        183,
                        249
                    ],
                    [
                        180,
                        83
                    ],
                    [
                        499,
                        22
                    ]
                ],
                "interior": []
            }
        },
        {
            "id": 44251172,
            "classId": 59069,
            "description": "",
            "geometryType": "polygon",
            "labelerLogin": "cx@datasetninja.com",
            "createdAt": "2023-09-15T12:55:04.161Z",
            "updatedAt": "2023-09-15T12:55:04.161Z",
            "tags": [],
            "classTitle": "column",
            "points": {
                "exterior": [
                    [
                        301,
                        278
                    ],
                    [
                        291,
                        281
                    ],
                    [
                        281,
                        280
                    ],
                    [
                        276,
                        277
                    ],
                    [
                        274,
                        57
                    ],
                    [
                        282,
                        53
                    ],
                    [
                        292,
                        54
                    ],
                    [
                        300,
                        56
                    ]
                ],
                "interior": []
            }
        },
        {
            "id": 44251171,
            "classId": 59069,
            "description": "",
            "geometryType": "polygon",
            "labelerLogin": "cx@datasetninja.com",
            "createdAt": "2023-09-15T12:55:04.161Z",
            "updatedAt": "2023-09-15T12:55:04.161Z",
            "tags": [],
            "classTitle": "column",
            "points": {
                "exterior": [
                    [
                        67,
                        229
                    ],
                    [
                        74,
                        231
                    ],
                    [
                        81,
                        231
                    ],
                    [
                        84,
                        228
                    ],
                    [
                        79,
                        102
                    ],
                    [
                        74,
                        102
                    ],
                    [
                        67,
                        102
                    ],
                    [
                        65,
                        104
                    ]
                ],
                "interior": []
            }
        },
        {
            "id": 44251170,
            "classId": 55073,
            "description": "",
            "geometryType": "polygon",
            "labelerLogin": "cx@datasetninja.com",
            "createdAt": "2023-09-15T12:55:04.161Z",
            "updatedAt": "2023-09-15T12:55:04.161Z",
            "tags": [],
            "classTitle": "floor",
            "points": {
                "exterior": [
                    [
                        0,
                        375
                    ],
                    [
                        2,
                        213
                    ],
                    [
                        11,
                        212
                    ],
                    [
                        11,
                        217
                    ],
                    [
                        16,
                        218
                    ],
                    [
                        31,
                        216
                    ],
                    [
                        65,
                        224
                    ],
                    [
                        67,
                        229
                    ],
                    [
                        74,
                        232
                    ],
                    [
                        83,
                        231
                    ],
                    [
                        86,
                        227
                    ],
                    [
                        150,
                        244
                    ],
                    [
                        146,
                        253
                    ],
                    [
                        156,
                        255
                    ],
                    [
                        182,
                        249
                    ],
                    [
                        276,
                        267
                    ],
                    [
                        276,
                        277
                    ],
                    [
                        284,
                        282
                    ],
                    [
                        295,
                        282
                    ],
                    [
                        301,
                        279
                    ],
                    [
                        301,
                        273
                    ],
                    [
                        499,
                        310
                    ],
                    [
                        499,
                        375
                    ]
                ],
                "interior": []
            }
        },
        {
            "id": 44251169,
            "classId": 64063,
            "description": "",
            "geometryType": "polygon",
            "labelerLogin": "cx@datasetninja.com",
            "createdAt": "2023-09-15T12:55:04.161Z",
            "updatedAt": "2023-09-15T12:55:04.161Z",
            "tags": [],
            "classTitle": "stand",
            "points": {
                "exterior": [
                    [
                        121,
                        177
                    ],
                    [
                        123,
                        243
                    ],
                    [
                        121,
                        246
                    ],
                    [
                        121,
                        253
                    ],
                    [
                        141,
                        257
                    ],
                    [
                        156,
                        250
                    ],
                    [
                        151,
                        180
                    ],
                    [
                        153,
                        180
                    ],
                    [
                        152,
                        176
                    ],
                    [
                        134,
                        177
                    ]
                ],
                "interior": []
            }
        },
        {
            "id": 44251168,
            "classId": 80989,
            "description": "",
            "geometryType": "polygon",
            "labelerLogin": "cx@datasetninja.com",
            "createdAt": "2023-09-15T12:55:04.160Z",
            "updatedAt": "2023-09-15T12:55:04.160Z",
            "tags": [],
            "classTitle": "picture",
            "points": {
                "exterior": [
                    [
                        88,
                        135
                    ],
                    [
                        103,
                        134
                    ],
                    [
                        104,
                        175
                    ],
                    [
                        88,
                        174
                    ]
                ],
                "interior": []
            }
        },
        {
            "id": 44251167,
            "classId": 80989,
            "description": "",
            "geometryType": "polygon",
            "labelerLogin": "cx@datasetninja.com",
            "createdAt": "2023-09-15T12:55:04.160Z",
            "updatedAt": "2023-09-15T12:55:04.160Z",
            "tags": [],
            "classTitle": "picture",
            "points": {
                "exterior": [
                    [
                        129,
                        135
                    ],
                    [
                        129,
                        173
                    ],
                    [
                        107,
                        173
                    ],
                    [
                        106,
                        136
                    ]
                ],
                "interior": []
            }
        },
        {
            "id": 44251166,
            "classId": 80989,
            "description": "",
            "geometryType": "polygon",
            "labelerLogin": "cx@datasetninja.com",
            "createdAt": "2023-09-15T12:55:04.160Z",
            "updatedAt": "2023-09-15T12:55:04.160Z",
            "tags": [],
            "classTitle": "picture",
            "points": {
                "exterior": [
                    [
                        188,
                        121
                    ],
                    [
                        219,
                        119
                    ],
                    [
                        220,
                        182
                    ],
                    [
                        188,
                        181
                    ]
                ],
                "interior": []
            }
        },
        {
            "id": 44251165,
            "classId": 80989,
            "description": "",
            "geometryType": "polygon",
            "labelerLogin": "cx@datasetninja.com",
            "createdAt": "2023-09-15T12:55:04.159Z",
            "updatedAt": "2023-09-15T12:55:04.159Z",
            "tags": [],
            "classTitle": "picture",
            "points": {
                "exterior": [
                    [
                        231,
                        104
                    ],
                    [
                        273,
                        100
                    ],
                    [
                        274,
                        147
                    ],
                    [
                        232,
                        149
                    ]
                ],
                "interior": []
            }
        },
        {
            "id": 44251164,
            "classId": 80989,
            "description": "",
            "geometryType": "polygon",
            "labelerLogin": "cx@datasetninja.com",
            "createdAt": "2023-09-15T12:55:04.159Z",
            "updatedAt": "2023-09-15T12:55:04.159Z",
            "tags": [],
            "classTitle": "picture",
            "points": {
                "exterior": [
                    [
                        234,
                        156
                    ],
                    [
                        273,
                        156
                    ],
                    [
                        274,
                        222
                    ],
                    [
                        235,
                        218
                    ]
                ],
                "interior": []
            }
        },
        {
            "id": 44251163,
            "classId": 80989,
            "description": "",
            "geometryType": "polygon",
            "labelerLogin": "cx@datasetninja.com",
            "createdAt": "2023-09-15T12:55:04.159Z",
            "updatedAt": "2023-09-15T12:55:04.159Z",
            "tags": [],
            "classTitle": "picture",
            "points": {
                "exterior": [
                    [
                        325,
                        83
                    ],
                    [
                        401,
                        74
                    ],
                    [
                        401,
                        146
                    ],
                    [
                        328,
                        149
                    ]
                ],
                "interior": []
            }
        },
        {
            "id": 44251162,
            "classId": 80989,
            "description": "",
            "geometryType": "polygon",
            "labelerLogin": "cx@datasetninja.com",
            "createdAt": "2023-09-15T12:55:04.159Z",
            "updatedAt": "2023-09-15T12:55:04.159Z",
            "tags": [],
            "classTitle": "picture",
            "points": {
                "exterior": [
                    [
                        327,
                        158
                    ],
                    [
                        399,
                        157
                    ],
                    [
                        400,
                        231
                    ],
                    [
                        327,
                        224
                    ]
                ],
                "interior": []
            }
        },
        {
            "id": 44251161,
            "classId": 80989,
            "description": "",
            "geometryType": "polygon",
            "labelerLogin": "cx@datasetninja.com",
            "createdAt": "2023-09-15T12:55:04.159Z",
            "updatedAt": "2023-09-15T12:55:04.159Z",
            "tags": [],
            "classTitle": "picture",
            "points": {
                "exterior": [
                    [
                        435,
                        98
                    ],
                    [
                        434,
                        196
                    ],
                    [
                        498,
                        198
                    ],
                    [
                        499,
                        93
                    ]
                ],
                "interior": []
            }
        },
        {
            "id": 44251160,
            "classId": 969511,
            "description": "",
            "geometryType": "polygon",
            "labelerLogin": "cx@datasetninja.com",
            "createdAt": "2023-09-15T12:55:04.159Z",
            "updatedAt": "2023-09-15T12:55:04.159Z",
            "tags": [],
            "classTitle": "ceiling spotlights",
            "points": {
                "exterior": [
                    [
                        166,
                        61
                    ],
                    [
                        382,
                        5
                    ],
                    [
                        426,
                        1
                    ],
                    [
                        426,
                        6
                    ],
                    [
                        391,
                        13
                    ],
                    [
                        391,
                        22
                    ],
                    [
                        396,
                        24
                    ],
                    [
                        394,
                        32
                    ],
                    [
                        388,
                        32
                    ],
                    [
                        387,
                        27
                    ],
                    [
                        381,
                        24
                    ],
                    [
                        387,
                        18
                    ],
                    [
                        389,
                        13
                    ],
                    [
                        331,
                        27
                    ],
                    [
                        329,
                        33
                    ],
                    [
                        333,
                        36
                    ],
                    [
                        333,
                        40
                    ],
                    [
                        332,
                        43
                    ],
                    [
                        326,
                        43
                    ],
                    [
                        326,
                        39
                    ],
                    [
                        321,
                        33
                    ],
                    [
                        328,
                        32
                    ],
                    [
                        328,
                        27
                    ],
                    [
                        284,
                        39
                    ],
                    [
                        286,
                        44
                    ],
                    [
                        289,
                        49
                    ],
                    [
                        281,
                        53
                    ],
                    [
                        278,
                        52
                    ],
                    [
                        276,
                        46
                    ],
                    [
                        282,
                        39
                    ],
                    [
                        243,
                        48
                    ],
                    [
                        244,
                        53
                    ],
                    [
                        246,
                        57
                    ],
                    [
                        246,
                        62
                    ],
                    [
                        241,
                        62
                    ],
                    [
                        238,
                        58
                    ],
                    [
                        236,
                        54
                    ],
                    [
                        242,
                        48
                    ],
                    [
                        208,
                        58
                    ],
                    [
                        209,
                        62
                    ],
                    [
                        213,
                        66
                    ],
                    [
                        210,
                        69
                    ],
                    [
                        205,
                        69
                    ],
                    [
                        204,
                        62
                    ],
                    [
                        208,
                        60
                    ],
                    [
                        208,
                        56
                    ],
                    [
                        177,
                        66
                    ],
                    [
                        178,
                        70
                    ],
                    [
                        182,
                        73
                    ],
                    [
                        180,
                        77
                    ],
                    [
                        175,
                        76
                    ],
                    [
                        172,
                        69
                    ],
                    [
                        176,
                        66
                    ]
                ],
                "interior": []
            }
        },
        {
            "id": 44251159,
            "classId": 176654,
            "description": "",
            "geometryType": "polygon",
            "labelerLogin": "cx@datasetninja.com",
            "createdAt": "2023-09-15T12:55:04.158Z",
            "updatedAt": "2023-09-15T12:55:04.158Z",
            "tags": [],
            "classTitle": "sprinkler",
            "points": {
                "exterior": [
                    [
                        85,
                        55
                    ],
                    [
                        78,
                        56
                    ],
                    [
                        78,
                        61
                    ],
                    [
                        80,
                        61
                    ],
                    [
                        80,
                        66
                    ],
                    [
                        82,
                        66
                    ],
                    [
                        83,
                        61
                    ],
                    [
                        84,
                        62
                    ]
                ],
                "interior": []
            }
        },
        {
            "id": 44251158,
            "classId": 176654,
            "description": "",
            "geometryType": "polygon",
            "labelerLogin": "cx@datasetninja.com",
            "createdAt": "2023-09-15T12:55:04.158Z",
            "updatedAt": "2023-09-15T12:55:04.158Z",
            "tags": [],
            "classTitle": "sprinkler",
            "points": {
                "exterior": [
                    [
                        231,
                        3
                    ],
                    [
                        220,
                        3
                    ],
                    [
                        220,
                        6
                    ],
                    [
                        223,
                        6
                    ],
                    [
                        224,
                        10
                    ],
                    [
                        225,
                        10
                    ],
                    [
                        225,
                        15
                    ],
                    [
                        228,
                        16
                    ],
                    [
                        227,
                        10
                    ],
                    [
                        229,
                        10
                    ],
                    [
                        229,
                        5
                    ],
                    [
                        233,
                        5
                    ]
                ],
                "interior": []
            }
        },
        {
            "id": 44251157,
            "classId": 89599,
            "description": "",
            "geometryType": "polygon",
            "labelerLogin": "cx@datasetninja.com",
            "createdAt": "2023-09-15T12:55:04.158Z",
            "updatedAt": "2023-09-15T12:55:04.158Z",
            "tags": [],
            "classTitle": "outlet",
            "points": {
                "exterior": [
                    [
                        392,
                        249
                    ],
                    [
                        397,
                        249
                    ],
                    [
                        397,
                        260
                    ],
                    [
                        392,
                        260
                    ]
                ],
                "interior": []
            }
        },
        {
            "id": 44251156,
            "classId": 123148,
            "description": "",
            "geometryType": "polygon",
            "labelerLogin": "cx@datasetninja.com",
            "createdAt": "2023-09-15T12:55:04.158Z",
            "updatedAt": "2023-09-15T12:55:04.158Z",
            "tags": [],
            "classTitle": "air vent",
            "points": {
                "exterior": [
                    [
                        108,
                        35
                    ],
                    [
                        85,
                        46
                    ],
                    [
                        129,
                        53
                    ],
                    [
                        150,
                        42
                    ]
                ],
                "interior": []
            }
        }
    ]
}